fastdrl/__init__.py
fastdrl/_nbdev.py
fastdrl/core.py
fastdrl-0.0.1.dist-info/LICENSE
fastdrl-0.0.1.dist-info/METADATA
fastdrl-0.0.1.dist-info/WHEEL
fastdrl-0.0.1.dist-info/entry_points.txt
fastdrl-0.0.1.dist-info/top_level.txt
fastdrl-0.0.1.dist-info/RECORD
